pyprodop/__init__.py
pyprodop/classes.py
pypulse/__init__.py
pypulse/classes.py
pyprodop-0.1a1.dist-info/LICENSE.txt
pyprodop-0.1a1.dist-info/METADATA
pyprodop-0.1a1.dist-info/WHEEL
pyprodop-0.1a1.dist-info/top_level.txt
pyprodop-0.1a1.dist-info/RECORD
